beholdr_io_metric_client/__init__.py
beholdr_io_metric_client/client.py
beholdr_io_metric_client/exceptions.py
beholdr_io_sdk-0.1.10.dist-info/LICENSE
beholdr_io_sdk-0.1.10.dist-info/METADATA
beholdr_io_sdk-0.1.10.dist-info/WHEEL
beholdr_io_sdk-0.1.10.dist-info/top_level.txt
beholdr_io_sdk-0.1.10.dist-info/RECORD
