Metadata-Version: 2.1
Name: beholdr_io_sdk
Version: 0.1.10
Summary: A Python SDK for interacting with Beholdr.io's Metrics API.
Author: Beholdr.io
Author-email: devin@beholdr.io
Classifier: Programming Language :: Python :: 3
Classifier: License :: OSI Approved :: Apache Software License
Classifier: Operating System :: OS Independent
Requires-Python: >=3.12
License-File: LICENSE
Requires-Dist: requests
